vodbot/__init__.py
vodbot/__main__.py
vodbot/cache.py
vodbot/chatlog.py
vodbot/config.py
vodbot/printer.py
vodbot/thumbnail.py
vodbot/twitch.py
vodbot/util.py
vodbot/video.py
vodbot/webhook.py
vodbot/commands/__init__.py
vodbot/commands/export.py
vodbot/commands/info.py
vodbot/commands/init.py
vodbot/commands/pull.py
vodbot/commands/stage.py
vodbot/commands/upload.py
vodbot/itd/__init__.py
vodbot/itd/download.py
vodbot/itd/gql.py
vodbot/itd/worker.py
VodBot-1.1.12.dist-info/LICENSE.md
VodBot-1.1.12.dist-info/METADATA
VodBot-1.1.12.dist-info/WHEEL
VodBot-1.1.12.dist-info/entry_points.txt
VodBot-1.1.12.dist-info/top_level.txt
VodBot-1.1.12.dist-info/RECORD
