Metadata-Version: 2.1
Name: VodBot
Version: 1.1.12
Summary: Twitch VOD and Clip manager
Home-page: https://github.com/FriendTeamInc/VodBot
Author: Logan "NotQuiteApex" Hickok-Dickson
Author-email: self@notquiteapex.net
License: MIT
Project-URL: Homepage, https://github.com/FriendTeamInc/VodBot
Project-URL: Bug Tracker, https://github.com/FriendTeamInc/VodBot/issues
Keywords: twitch youtube vod video clip download
Requires-Python: >=3.7
License-File: LICENSE.md
Requires-Dist: Pillow >=9.4.0
Requires-Dist: argcomplete >=2.0.0
Requires-Dist: dataclasses-json >=0.5.7
Requires-Dist: discord-webhook >=1.0.0
Requires-Dist: google-api-python-client >=2.70.0
Requires-Dist: google-auth-httplib2 >=0.1.0
Requires-Dist: google-auth-oauthlib >=0.8.0
Requires-Dist: m3u8 >=3.3.0
Requires-Dist: requests >=2.28.1
